racket/__init__.py
racket/conf.py
racket/main.py
racket/utils.py
racket/template/.gitignore
racket/template/Dockerfile.racket
racket/template/Dockerfile.tfserving
racket/template/classification.py
racket/template/docker-compose.yaml
racket/template/racket.yaml
racket/template/serialized/base_1.h5
racket/template/serialized/base_1.json
racket/template/serialized/base_history_1.json
racket/template/serialized/base/1/saved_model.pb
racket/template/serialized/base/1/variables/variables.data-00000-of-00001
racket/template/serialized/base/1/variables/variables.index
racket/template/web/asset-manifest.json
racket/template/web/index.html
racket/template/web/manifest.json
racket/template/web/precache-manifest.fcfb7db48cf4170e365493e03a9a3451.js
racket/template/web/service-worker.js
racket/template/web/static/css/main.8b7936fd.chunk.css
racket/template/web/static/css/main.8b7936fd.chunk.css.map
racket/template/web/static/js/1.a95de961.chunk.js
racket/template/web/static/js/1.a95de961.chunk.js.map
racket/template/web/static/js/main.77f4b719.chunk.js
racket/template/web/static/js/main.77f4b719.chunk.js.map
racket/template/web/static/js/runtime~main.229c360f.js
racket/template/web/static/js/runtime~main.229c360f.js.map
racket-0.3.9.dist-info/DESCRIPTION.rst
racket-0.3.9.dist-info/METADATA
racket-0.3.9.dist-info/RECORD
racket-0.3.9.dist-info/WHEEL
racket-0.3.9.dist-info/entry_points.txt
racket-0.3.9.dist-info/metadata.json
racket-0.3.9.dist-info/top_level.txt
