Metadata-Version: 2.0
Name: racket
Version: 0.3.9
Summary: Serve your models with confidence
Home-page: https://github.com/carlomazzaferro/racket
Author: Carlo Mazzaferro
Author-email: carlo.mazzaferro@gmail.com
License: GNU General Public License v3
Keywords: racket
Platform: UNKNOWN
Classifier: Development Status :: 2 - Pre-Alpha
Classifier: Intended Audience :: Developers
Classifier: License :: OSI Approved :: GNU General Public License v3 (GPLv3)
Classifier: Natural Language :: English
Classifier: Programming Language :: Python :: 3.6
Classifier: Programming Language :: Python :: 3.7
Provides-Extra: gpu
Requires-Dist: tensorflow (<2,>=1.12.1)
Requires-Dist: tensorflow-serving-api (==1.11.1)
Requires-Dist: grpcio (==1.16.0)
Requires-Dist: Flask (==1.0.2)
Requires-Dist: flask-restplus (==0.12.1)
Requires-Dist: Flask-Cors (==3.0.7)
Requires-Dist: Flask-SQLAlchemy (==2.4.0)
Requires-Dist: Click (>=6.0)
Requires-Dist: pyyaml (>=4.2b1)
Requires-Dist: tabulate (==0.8.2)
Requires-Dist: gevent (==1.4.0)
Requires-Dist: gunicorn (==19.9.0)
Provides-Extra: gpu
Requires-Dist: tensorflow-gpu (==1.11.0); extra == 'gpu'
